luma/classifier/discriminant.py
luma/classifier/logistic.py
luma/classifier/naive_bayes.py
luma/classifier/neighbors.py
luma/classifier/svm.py
luma/classifier/tree.py
luma/clustering/affinity.py
luma/clustering/density.py
luma/clustering/hierarchy.py
luma/clustering/kmeans.py
luma/clustering/mixture.py
luma/clustering/spectral.py
luma/core/base.py
luma/core/main.py
luma/core/super.py
luma/ensemble/bagging.py
luma/ensemble/boost.py
luma/ensemble/forest.py
luma/ensemble/stack.py
luma/ensemble/vote.py
luma/extension/__init__.py
luma/extension/func_deco.py
luma/interface/exception.py
luma/interface/typing.py
luma/interface/util.py
luma/metric/classification.py
luma/metric/clustering.py
luma/metric/distance.py
luma/metric/regression.py
luma/migrate/port.py
luma/model_selection/cv.py
luma/model_selection/fold.py
luma/model_selection/search.py
luma/model_selection/split.py
luma/neural/__init__.py
luma/neural/base.py
luma/neural/functional.py
luma/neural/init.py
luma/neural/loss.py
luma/neural/optimizer.py
luma/neural/scheduler.py
luma/neural/single.py
luma/neural/autoprop/__init__.py
luma/neural/autoprop/graph.py
luma/neural/autoprop/merge.py
luma/neural/block/__init__.py
luma/neural/block/convnext.py
luma/neural/block/dense.py
luma/neural/block/efficient.py
luma/neural/block/incep.py
luma/neural/block/incep_res.py
luma/neural/block/mobile.py
luma/neural/block/resnest.py
luma/neural/block/resnet.py
luma/neural/block/se.py
luma/neural/block/sk.py
luma/neural/block/standard.py
luma/neural/block/transformer.py
luma/neural/block/xception.py
luma/neural/layer/__init__.py
luma/neural/layer/act.py
luma/neural/layer/attend.py
luma/neural/layer/conv.py
luma/neural/layer/drop.py
luma/neural/layer/encode.py
luma/neural/layer/linear.py
luma/neural/layer/norm.py
luma/neural/layer/pool.py
luma/neural/layer/util.py
luma/neural/model/__init__.py
luma/neural/model/simple.py
luma/neural/model/types.py
luma/neural/model/img_clf/__init__.py
luma/neural/model/img_clf/alex.py
luma_ml-1.2.5.dist-info/LICENSE
luma_ml-1.2.5.dist-info/METADATA
luma_ml-1.2.5.dist-info/WHEEL
luma_ml-1.2.5.dist-info/top_level.txt
luma_ml-1.2.5.dist-info/RECORD
