Metadata-Version: 2.1
Name: luma-ml
Version: 1.2.5
Summary: A Comprehensive Python Module for Machine Learning and Data Science
Home-page: https://github.com/ChanLumerico/luma
Author: ChanLumerico
Author-email: greensox284@gmail.com
Classifier: Programming Language :: Python :: 3
Classifier: License :: OSI Approved :: GNU General Public License v3 (GPLv3)
Classifier: Operating System :: OS Independent
Requires-Python: >=3.12
License-File: LICENSE
Requires-Dist: numpy
Requires-Dist: scipy
Requires-Dist: pandas
Requires-Dist: matplotlib
Requires-Dist: seaborn
Requires-Dist: rich
